[
    {
      "date": "2025-05-02T15:30:00",
      "teamA": "Equipo A",
      "teamB": "Equipo B",
      "format": "1 set de 25 pts",
      "scoreA": null,
      "scoreB": null,
      "playersStats": {}
    },
    {
      "date": "2025-05-02T16:00:00",
      "teamA": "Equipo C",
      "teamB": "Equipo D",
      "format": "1 set de 25 pts",
      "scoreA": null,
      "scoreB": null,
      "playersStats": {}
    },
    {
      "date": "2025-05-09T15:30:00",
      "teamA": "Equipo A",
      "teamB": "Equipo C",
      "format": "1 set de 25 pts",
      "scoreA": null,
      "scoreB": null,
      "playersStats": {}
    },
    {
      "date": "2025-05-09T16:00:00",
      "teamA": "Equipo B",
      "teamB": "Equipo D",
      "format": "1 set de 25 pts",
      "scoreA": null,
      "scoreB": null,
      "playersStats": {}
    },
    {
      "date": "2025-05-16T15:30:00",
      "teamA": "Equipo A",
      "teamB": "Equipo D",
      "format": "1 set de 25 pts",
      "scoreA": null,
      "scoreB": null,
      "playersStats": {}
    },
    {
      "date": "2025-05-16T16:00:00",
      "teamA": "Equipo B",
      "teamB": "Equipo C",
      "format": "1 set de 25 pts",
      "scoreA": null,
      "scoreB": null,
      "playersStats": {}
    },
    {
      "date": "2025-05-23T15:30:00",
      "teamA": "",
      "teamB": "",
      "match": "Semifinal 1",
      "format": "3 sets de 15 pts",
      "scoreA": null,
      "scoreB": null,
      "playersStats": {}
    },
    {
      "date": "2025-05-23T16:00:00",
      "teamA": "",
      "teamB": "",
      "match": "Semifinal 2",
      "format": "3 sets de 15 pts",
      "scoreA": null,
      "scoreB": null,
      "playersStats": {}
    },
    {
      "date": "2025-05-30T15:30:00",
      "teamA": "",
      "teamB": "",
      "match": "Tercer Puesto",
      "format": "3 sets de 10 pts",
      "scoreA": null,
      "scoreB": null,
      "playersStats": {}
    },
    {
      "date": "2025-05-30T16:00:00",
      "teamA": "",
      "teamB": "",
      "match": "Final",
      "format": "3 sets de 15 pts",
      "scoreA": null,
      "scoreB": null,
      "playersStats": {}
    }
  ]
  